req_updater/__init__.py
req_updater/__main__.py
req_updater/updater.py
req_updater-0.1.0.dist-info/licenses/LICENSE
req_updater-0.1.0.dist-info/METADATA
req_updater-0.1.0.dist-info/WHEEL
req_updater-0.1.0.dist-info/entry_points.txt
req_updater-0.1.0.dist-info/top_level.txt
req_updater-0.1.0.dist-info/RECORD
