Metadata-Version: 2.4
Name: req-updater
Version: 0.1.0
Summary: Automatically updates package versions in requirements.txt files
Author-email: Sohail Ahmad <sohailahmad34280@gmail.com>
License: MIT
Project-URL: Homepage, https://github.com/Sohail342/req-updater
Project-URL: Issues, https://github.com/Sohail342/req-updater/issues
Classifier: Programming Language :: Python :: 3
Classifier: License :: OSI Approved :: MIT License
Classifier: Operating System :: OS Independent
Requires-Python: >=3.7
License-File: LICENSE
Requires-Dist: packaging>=21.0
Provides-Extra: dev
Requires-Dist: pytest>=6.0; extra == "dev"
Requires-Dist: pytest-cov>=2.0; extra == "dev"
Requires-Dist: black>=21.0; extra == "dev"
Requires-Dist: flake8>=3.8; extra == "dev"
Dynamic: license-file
